pwnedpass/__init__.py
pwnedpass/__main__.py
pwnedpass/constants.py
pwnedpass/rewrite.py
pwnedpass-1.0.0.dist-info/LICENSE
pwnedpass-1.0.0.dist-info/METADATA
pwnedpass-1.0.0.dist-info/WHEEL
pwnedpass-1.0.0.dist-info/entry_points.txt
pwnedpass-1.0.0.dist-info/top_level.txt
pwnedpass-1.0.0.dist-info/RECORD
