Metadata-Version: 2.1
Name: pwnedpass
Version: 1.0.0
Summary: Queries a local instance of Troy Hunt's Pwned Passwords database. (Port of https://github.com/tylerchr/pwnedpass)
Home-page: https://git.csdisaster.club/io/pwnedpass
Author: io
License: BSD-3-Clause
Platform: UNKNOWN
Classifier: Development Status :: 5 - Production/Stable
Classifier: Environment :: Console
Classifier: Intended Audience :: Developers
Classifier: Intended Audience :: End Users/Desktop
Classifier: Topic :: Utilities
Classifier: Natural Language :: English
Classifier: Operating System :: OS Independent
Classifier: License :: OSI Approved :: BSD License
Requires-Python: >=3.6.0
License-File: LICENSE
